Metadata-Version: 2.1
Name: Vigilant
Version: 1.0.1
Summary: Create and run tests easily.
Home-page: https://github.com/ZSendokame/Vigilant
Author: ZSendokame
License: MIT license
Platform: UNKNOWN
